cookies_utilities/__init__.py
cookies_utilities/datetime.py
cookies_utilities/diff.py
cookies_utilities/html_helper.py
cookies_utilities/stopwatch.py
cookies_utilities-0.0.4.dist-info/METADATA
cookies_utilities-0.0.4.dist-info/WHEEL
cookies_utilities-0.0.4.dist-info/licenses/LICENSE
cookies_utilities-0.0.4.dist-info/RECORD
