Metadata-Version: 2.1
Name: cookies_utilities
Version: 0.0.4
Summary: Utility functions.
Project-URL: GitHub, https://github.com/CookieBox26/cookies_utilities
Project-URL: Documentation, https://cookies-utilities.readthedocs.io/en/stable/
Author-email: CookieBox26 <cookie-box@cookie-box.info>
License-File: LICENSE
Classifier: License :: OSI Approved :: MIT License
Classifier: Operating System :: OS Independent
Classifier: Programming Language :: Python :: 3
Requires-Python: >=3.8
Provides-Extra: docs
Requires-Dist: sphinx-rtd-theme; extra == 'docs'
